<?xml version="1.0" ?>
<container xmlns="http://symfony.com/schema/dic/services"
           xmlns:xsi="http://www.w3.org/2001/XMLSchema-instance"
           xsi:schemaLocation="http://symfony.com/schema/dic/services http://symfony.com/schema/dic/services/services-1.0.xsd">

    <services>

        <service id="MichaPriceOnRequest\Subscriber\MySubscriber">
            <argument type="service" id="Shopware\Core\System\SystemConfig\SystemConfigService"/>
            <tag name="kernel.event_subscriber"/>
        </service>

        <service id="MichaPriceOnRequest\Storefront\Controller\ExampleController" public="true">
            <argument type="service" id="Shopware\Core\System\SystemConfig\SystemConfigService"/>
            <argument type="service" id="mailer.mailer"/>
            <argument type="service" id="MichaPriceOnRequest\Service\RateLimiter"/>
            <call method="setContainer">
                <argument type="service" id="service_container"/>
            </call>
        </service>

        <service id="MichaPriceOnRequest\Service\RateLimiter"/>

        <service id="MichaPriceOnRequest\Storefront\Controller\ExampleController" public="true">
            <argument type="service" id="Shopware\Core\System\SystemConfig\SystemConfigService"/>
            <argument type="service" id="mailer.mailer"/>
            <argument type="service" id="MichaPriceOnRequest\Service\RateLimiter"/>
            <call method="setContainer">
                <argument type="service" id="service_container"/>
            </call>
        </service>

    </services>
</container>